Workbook
Name Slicer_Bank_Type: #N/A
Name Slicer_Year: #N/A

Sheet Raw Data
A1: Bank | B1: Bank_Type | C1: Year | D1: Total Assets | E1: Total Deposits | F1: Total Equity | G1: Cash | H1: Financing/Loans | I1: Operating Income | J1: Operating Expenses | K1: Staff Expenses | L1: Net Profit | M1: Profit Distributed | N1: Staff Strength
A2: Askari | B2: Conventional | C2: 2019 | D2: 833208006 | E2: 679299486 | F2: 42255844 | G2: 63039290 | H2: 372913863 | I2: 29539997 | J2: 18235387 | K2: 8783319 | L2: 7017022 | M2: 1890390 | N2: 7848
A3: Askari | B3: Conventional | C3: 2020 | D3: 992517062 | E3: 791186883 | F3: 54546350 | G3: 73651718 | H3: 395373840 | I3: 39956618 | J3: 20123495 | K3: 11551156 | L3: 10800375 | M3: 3780781 | N3: 7949
A4: Askari | B4: Conventional | C4: 2021 | D4: 1259144109 | E4: 1015430068 | F4: 55902493 | G4: 89432245 | H4: 477588237 | I4: 41779371 | J4: 20890525 | K4: 11720691 | L4: 9701386 | M4: 0 | N4: 7478
A5: Askari | B5: Conventional | C5: 2022 | D5: 1526133734 | E5: 1142574606 | F5: 73322253 | G5: 70950067 | H5: 583810931 | I5: 51581558 | J5: 22572388 | K5: 11474947 | L5: 14061595 | M5: 1890390 | N5: 7348
A6: Askari | B6: Conventional | C6: 2023 | D6: 2124005959 | E6: 1293145575 | F6: 97122821 | G6: 160087394 | H6: 633132827 | I6: 72358907 | J6: 28569430 | K6: 14417616 | L6: 21434659 | M6: 3623248 | N6: 7881
A7: Askari | B7: Conventional | C7: 2024 | D7: 2498374205 | E7: 1363735115 | F7: 121628559 | G7: 133505285 | H7: 695758143 | I7: 78720528 | J7: 35408493 | K7: 17090815 | L7: 21022671 | M7: 4347898 | N7: 8269
A8: HBL | B8: Conventional | C8: 2019 | D8: 3053733753 | E8: 2301899086 | F8: 201421946 | G8: 337241623 | H8: 1073018669 | I8: 113384890 | J8: 82709202 | K8: 29757054 | L8: 15064189 | M8: 7336000 | N8: 17353
A9: HBL | B9: Conventional | C9: 2020 | D9: 3643711720 | E9: 2669490716 | F9: 242724765 | G9: 347988749 | H9: 1117320960 | I9: 147794767 | J9: 83151607 | K9: 33639523 | L9: 31523682 | M9: 3668000 | N9: 16954
A10: HBL | B10: Conventional | C10: 2021 | D10: 4074588206 | E10: 3184260887 | F10: 257928910 | G10: 409528880 | H10: 1384549476 | I10: 151671703 | J10: 84607713 | K10: 33697001 | L10: 34271494 | M10: 12102000 | N10: 17591
A11: HBL | B11: Conventional | C11: 2022 | D11: 4355096917 | E11: 3234176418 | F11: 253775516 | G11: 257368084 | H11: 1622607447 | I11: 190393360 | J11: 110475260 | K11: 41532374 | L11: 30867003 | M11: 11000000 | N11: 17602
A12: HBL | B12: Conventional | C12: 2023 | D12: 5201671163 | E12: 3870179912 | F12: 333779408 | G12: 505181227 | H12: 1664016203 | I12: 277297213 | J12: 152339336 | K12: 50737676 | L12: 56855995 | M12: 10634000 | N12: 16353
A13: HBL | B13: Conventional | C13: 2024 | D13: 5659803830 | E13: 4091168379 | F13: 377785296 | G13: 421135641 | H13: 2254964431 | I13: 313235711 | J13: 170661897 | K13: 56506395 | L13: 56765819 | M13: 23469000 | N13: 16533
... A25: Meezan | B25: Islamic | C25: 2024 | D25: 3900411330 | E25: 2584871300 | F25: 246984292 | G25: 260734258 | H25: 1514755936 | I25: 315917305 | J25: 79509599 | K25: 43732513 | L25: 101507524 | M25: 51995169 | N25: 18653
A26: Dubai Islamic Bank | B26: Islamic | C26: 2019 | D26: 264638618 | E26: 209952073 | F26: 22162634 | G26: 19417428 | H26: 177921837 | I26: 13283535 | J26: 6658707 | L26: 3345597 | N26: 3095
A27: Dubai Islamic Bank | B27: Islamic | C27: 2020 | D27: 303262163 | E27: 237553365 | F27: 24623698 | G27: 19096891 | H27: 199416405 | I27: 14390574 | J27: 7369672 | L27: 2893891 | N27: 3099
A28: Dubai Islamic Bank | B28: Islamic | C28: 2021 | D28: 351474159 | E28: 261573620 | F28: 27567059 | G28: 25761239 | H28: 225364893 | I28: 15553444 | J28: 8285564 | L28: 3089310 | N28: 3223
A29: Dubai Islamic Bank | B29: Islamic | C29: 2022 | D29: 445390462 | E29: 345811211 | F29: 30106817 | G29: 45632108 | H29: 247767953 | I29: 22949607 | J29: 10132049 | L29: 3915574 | N29: 3468
A30: Dubai Islamic Bank | B30: Islamic | C30: 2023 | D30: 430992381 | E30: 324876776 | F30: 37164885 | G30: 28901856 | H30: 243067943 | I30: 34231411 | J30: 12405406 | L30: 6719179 | N30: 3434
A31: Dubai Islamic Bank | B31: Islamic | C31: 2024 | D31: 452889701 | E31: 346872762 | F31: 44946559 | G31: 30433179 | H31: 203608460 | I31: 34204924 | J31: 15839586 | L31: 6671595 | N31: 3774
A32: BankIslami | B32: Islamic | C32: 2019 | D32: 283096494 | E32: 228826675 | F32: 19696332 | G32: 14640163 | H32: 131774504 | I32: 12423575 | J32: 7721165 | K32: 3090808 | L32: 1087338 | M32: 0 | N32: 3447
A33: BankIslami | B33: Islamic | C33: 2020 | D33: 336297298 | E33: 282015950 | F33: 19895173 | G33: 22034025 | H33: 130161889 | I33: 14124337 | J33: 8578042 | K33: 3619430 | L33: 1703135 | M33: 0 | N33: 3437
A34: BankIslami | B34: Islamic | C34: 2021 | D34: 408390174 | E34: 344787956 | F34: 22511202 | G34: 24552347 | H34: 181176239 | I34: 13051626 | J34: 9549614 | K34: 4398458 | L34: 2131350 | M34: 0 | N34: 4046
A35: BankIslami | B35: Islamic | C35: 2022 | D35: 487239112 | E35: 415911942 | F35: 26450401 | G35: 39972702 | H35: 201328442 | I35: 24001221 | J35: 11773169 | K35: 5363050 | L35: 4439635 | M35: 1109000 | N35: 4562
A36: BankIslami | B36: Islamic | C36: 2023 | D36: 654865896 | E36: 522540925 | F36: 36465918 | G36: 41287071 | H36: 230194288 | I36: 43494329 | J36: 16159656 | K36: 7493260 | L36: 11045099 | M36: 3049000 | N36: 5891
A37: BankIslami | B37: Islamic | C37: 2024 | D37: 737834025 | E37: 559177932 | F37: 48309276 | G37: 41093952 | H37: 296018363 | I37: 50977162 | J37: 22159072 | K37: 9947120 | L37: 11833541 | M37: 2772000 | N37: 7317

Sheet Ratios
A1: Bank | B1: Bank Type | C1: Years | D1: Operating Expense Ratio | E1: Cost-to-Income Ratio | F1: ROA | G1: ROE | H1: Cash-to-Assets Ratio | I1: Financing-to-Assets Ratio | J1: Bank Size
A2: =('Raw Data'!A2) -> Askari | B2: =('Raw Data'!B2) -> Conventional | C2: =('Raw Data'!C2) -> 2019 | D2: =('Raw Data'!J2)/('Raw Data'!D2) -> 0.021885756 | E2: ='Raw Data'!J2/'Raw Data'!I2 -> 0.61731174 | F2: ='Raw Data'!L2/'Raw Data'!D2 -> 0.008421693 | G2: ='Raw Data'!L2/'Raw Data'!F2 -> 0.16606039 | H2: ='Raw Data'!G2/'Raw Data'!D2 -> 0.075658526 | I2: ='Raw Data'!H2/'Raw Data'!D2 -> 0.44756395 | J2: =LN('Raw Data'!D2) -> 20.540794
A3: =('Raw Data'!A3) -> Askari | B3: =('Raw Data'!B3) -> Conventional | C3: =('Raw Data'!C3) -> 2020 | D3: =('Raw Data'!J3)/('Raw Data'!D3) -> 0.020275213 | E3: ='Raw Data'!J3/'Raw Data'!I3 -> 0.50363359 | F3: ='Raw Data'!L3/'Raw Data'!D3 -> 0.010881803 | G3: ='Raw Data'!L3/'Raw Data'!F3 -> 0.19800362 | H3: ='Raw Data'!G3/'Raw Data'!D3 -> 0.074207004 | I3: ='Raw Data'!H3/'Raw Data'!D3 -> 0.3983547 | J3: =LN('Raw Data'!D3) -> 20.715755
A4: =('Raw Data'!A4) -> Askari | B4: =('Raw Data'!B4) -> Conventional | C4: =('Raw Data'!C4) -> 2021 | D4: =('Raw Data'!J4)/('Raw Data'!D4) -> 0.016591052 | E4: ='Raw Data'!J4/'Raw Data'!I4 -> 0.50002009 | F4: ='Raw Data'!L4/'Raw Data'!D4 -> 0.0077047464 | G4: ='Raw Data'!L4/'Raw Data'!F4 -> 0.17354121 | H4: ='Raw Data'!G4/'Raw Data'!D4 -> 0.071026219 | I4: ='Raw Data'!H4/'Raw Data'!D4 -> 0.37929593 | J4: =LN('Raw Data'!D4) -> 20.953698
A5: =('Raw Data'!A5) -> Askari | B5: =('Raw Data'!B5) -> Conventional | C5: =('Raw Data'!C5) -> 2022 | D5: =('Raw Data'!J5)/('Raw Data'!D5) -> 0.01479057 | E5: ='Raw Data'!J5/'Raw Data'!I5 -> 0.43760578 | F5: ='Raw Data'!L5/'Raw Data'!D5 -> 0.0092138681 | G5: ='Raw Data'!L5/'Raw Data'!F5 -> 0.191778 | H5: ='Raw Data'!G5/'Raw Data'!D5 -> 0.046490072 | I5: ='Raw Data'!H5/'Raw Data'!D5 -> 0.38254245 | J5: =LN('Raw Data'!D5) -> 21.146003
A6: =('Raw Data'!A6) -> Askari | B6: =('Raw Data'!B6) -> Conventional | C6: =('Raw Data'!C6) -> 2023 | D6: =('Raw Data'!J6)/('Raw Data'!D6) -> 0.01345073 | E6: ='Raw Data'!J6/'Raw Data'!I6 -> 0.39482949 | F6: ='Raw Data'!L6/'Raw Data'!D6 -> 0.010091619 | G6: ='Raw Data'!L6/'Raw Data'!F6 -> 0.22069642 | H6: ='Raw Data'!G6/'Raw Data'!D6 -> 0.075370501 | I6: ='Raw Data'!H6/'Raw Data'!D6 -> 0.2980843 | J6: =LN('Raw Data'!D6) -> 21.47657
A7: =('Raw Data'!A7) -> Askari | B7: =('Raw Data'!B7) -> Conventional | C7: =('Raw Data'!C7) -> 2024 | D7: =('Raw Data'!J7)/('Raw Data'!D7) -> 0.014172614 | E7: ='Raw Data'!J7/'Raw Data'!I7 -> 0.44979999 | F7: ='Raw Data'!L7/'Raw Data'!D7 -> 0.0084145405 | G7: ='Raw Data'!L7/'Raw Data'!F7 -> 0.17284321 | H7: ='Raw Data'!G7/'Raw Data'!D7 -> 0.053436865 | I7: ='Raw Data'!H7/'Raw Data'!D7 -> 0.27848436 | J7: =LN('Raw Data'!D7) -> 21.638906
A8: =('Raw Data'!A8) -> HBL | B8: =('Raw Data'!B8) -> Conventional | C8: =('Raw Data'!C8) -> 2019 | D8: =('Raw Data'!J8)/('Raw Data'!D8) -> 0.027084615 | E8: ='Raw Data'!J8/'Raw Data'!I8 -> 0.72945524 | F8: ='Raw Data'!L8/'Raw Data'!D8 -> 0.0049330394 | G8: ='Raw Data'!L8/'Raw Data'!F8 -> 0.074789214 | H8: ='Raw Data'!G8/'Raw Data'!D8 -> 0.11043583 | I8: ='Raw Data'!H8/'Raw Data'!D8 -> 0.35137925 | J8: =LN('Raw Data'!D8) -> 21.839631
A9: =('Raw Data'!A9) -> HBL | B9: =('Raw Data'!B9) -> Conventional | C9: =('Raw Data'!C9) -> 2020 | D9: =('Raw Data'!J9)/('Raw Data'!D9) -> 0.022820578 | E9: ='Raw Data'!J9/'Raw Data'!I9 -> 0.56261537 | F9: ='Raw Data'!L9/'Raw Data'!D9 -> 0.0086515302 | G9: ='Raw Data'!L9/'Raw Data'!F9 -> 0.12987419 | H9: ='Raw Data'!G9/'Raw Data'!D9 -> 0.095503919 | I9: ='Raw Data'!H9/'Raw Data'!D9 -> 0.30664362 | J9: =LN('Raw Data'!D9) -> 22.016269
A10: =('Raw Data'!A10) -> HBL | B10: =('Raw Data'!B10) -> Conventional | C10: =('Raw Data'!C10) -> 2021 | D10: =('Raw Data'!J10)/('Raw Data'!D10) -> 0.020764727 | E10: ='Raw Data'!J10/'Raw Data'!I10 -> 0.55783453 | F10: ='Raw Data'!L10/'Raw Data'!D10 -> 0.0084110325 | G10: ='Raw Data'!L10/'Raw Data'!F10 -> 0.13287186 | H10: ='Raw Data'!G10/'Raw Data'!D10 -> 0.10050804 | I10: ='Raw Data'!H10/'Raw Data'!D10 -> 0.33980108 | J10: =LN('Raw Data'!D10) -> 22.128036
A11: =('Raw Data'!A11) -> HBL | B11: =('Raw Data'!B11) -> Conventional | C11: =('Raw Data'!C11) -> 2022 | D11: =('Raw Data'!J11)/('Raw Data'!D11) -> 0.025366889 | E11: ='Raw Data'!J11/'Raw Data'!I11 -> 0.58024744 | F11: ='Raw Data'!L11/'Raw Data'!D11 -> 0.0070875582 | G11: ='Raw Data'!L11/'Raw Data'!F11 -> 0.12163113 | H11: ='Raw Data'!G11/'Raw Data'!D11 -> 0.059095834 | I11: ='Raw Data'!H11/'Raw Data'!D11 -> 0.37257666 | J11: =LN('Raw Data'!D11) -> 22.194613
A12: =('Raw Data'!A12) -> HBL | B12: =('Raw Data'!B12) -> Conventional | C12: =('Raw Data'!C12) -> 2023 | D12: =('Raw Data'!J12)/('Raw Data'!D12) -> 0.029286614 | E12: ='Raw Data'!J12/'Raw Data'!I12 -> 0.54937204 | F12: ='Raw Data'!L12/'Raw Data'!D12 -> 0.010930332 | G12: ='Raw Data'!L12/'Raw Data'!F12 -> 0.17034003 | H12: ='Raw Data'!G12/'Raw Data'!D12 -> 0.097119024 | I12: ='Raw Data'!H12/'Raw Data'!D12 -> 0.31990031 | J12: =LN('Raw Data'!D12) -> 22.372246
A13: =('Raw Data'!A13) -> HBL | B13: =('Raw Data'!B13) -> Conventional | C13: =('Raw Data'!C13) -> 2024 | D13: =('Raw Data'!J13)/('Raw Data'!D13) -> 0.030153324 | E13: ='Raw Data'!J13/'Raw Data'!I13 -> 0.54483538 | F13: ='Raw Data'!L13/'Raw Data'!D13 -> 0.010029644 | G13: ='Raw Data'!L13/'Raw Data'!F13 -> 0.15025947 | H13: ='Raw Data'!G13/'Raw Data'!D13 -> 0.074408169 | I13: ='Raw Data'!H13/'Raw Data'!D13 -> 0.39841742 | J13: =LN('Raw Data'!D13) -> 22.456655
... A37: =('Raw Data'!A37) -> BankIslami | B37: =('Raw Data'!B37) -> Islamic | C37: =('Raw Data'!C37) -> 2024 | D37: =('Raw Data'!J37)/('Raw Data'!D37) -> 0.030032597 | E37: ='Raw Data'!J37/'Raw Data'!I37 -> 0.43468626 | F37: ='Raw Data'!L37/'Raw Data'!D37 -> 0.016038215 | G37: ='Raw Data'!L37/'Raw Data'!F37 -> 0.24495381 | H37: ='Raw Data'!G37/'Raw Data'!D37 -> 0.055695388 | I37: ='Raw Data'!H37/'Raw Data'!D37 -> 0.40119912 | J37: =LN('Raw Data'!D37) -> 20.419229

Sheet Descriptive Statistics
A1: Statistic | B1: Operating Expense Ratio | C1: Cost-to-Income Ratio | D1: ROA | E1: ROE | F1: Cash-to-Assets Ratio | G1: Financing-to-Assets Ratio | H1: Bank Size
A2: Mean | B2: =AVERAGE(Ratios!D2:D37) -> 0.024156497 | C2: =AVERAGE(Table5[Cost-to-Income Ratio]) -> 0.53662922 | D2: =AVERAGE(Table5[ROA]) -> 0.010095178 | E2: =AVERAGE(Table5[ROE]) -> 0.17199933 | F2: =AVERAGE(Table5[Cash-to-Assets Ratio]) -> 0.071100491 | G2: =AVERAGE(Table5[Financing-to-Assets Ratio]) -> 0.41783386 | H2: =AVERAGE(Table5[[Bank Size ]]) -> 20.759297
A3: Median | B3: =MEDIAN(Table5[Operating Expense Ratio]) -> 0.023478652 | C3: =MEDIAN(Table5[Cost-to-Income Ratio]) -> 0.5078758 | D3: =MEDIAN(Table5[ROA]) -> 0.0089515743 | E3: =MEDIAN(Table5[ROE]) -> 0.15060806 | F3: =MEDIAN(Table5[Cash-to-Assets Ratio]) -> 0.0685352 | G3: =MEDIAN(Table5[Financing-to-Assets Ratio]) -> 0.39335635 | H3: =MEDIAN(Table5[[Bank Size ]]) -> 20.480012
A4: Standard Deviation | B4: =_xlfn.STDEV.S(Table5[Operating Expense Ratio]) -> 0.006260677 | C4: =_xlfn.STDEV.S(Table5[Cost-to-Income Ratio]) -> 0.16104071 | D4: =_xlfn.STDEV.S(Table5[ROA]) -> 0.0061161231 | E4: =_xlfn.STDEV.S(Table5[ROE]) -> 0.10754884 | F4: =_xlfn.STDEV.S(Table5[Cash-to-Assets Ratio]) -> 0.016907931 | G4: =_xlfn.STDEV.S(Table5[Financing-to-Assets Ratio]) -> 0.09823329 | H4: =_xlfn.STDEV.S(Table5[[Bank Size ]]) -> 0.95004388
A5: Minimum | B5: =MIN(Table5[Operating Expense Ratio]) -> 0.01345073 | C5: =MIN(Table5[Cost-to-Income Ratio]) -> 0.25167852 | D5: =MIN(Table5[ROA]) -> 5.2405584e-05 | E5: =MIN(Table5[ROE]) -> 0.0014222949 | F5: =MIN(Table5[Cash-to-Assets Ratio]) -> 0.040156226 | G5: =MIN(Table5[Financing-to-Assets Ratio]) -> 0.27848436 | H5: =MIN(Table5[[Bank Size ]]) -> 19.393876
A6: Maximum | B6: =MAX(Table5[Operating Expense Ratio]) -> 0.042989977 | C6: =MAX(Table5[Cost-to-Income Ratio]) -> 0.98360735 | D6: =MAX(Table5[ROA]) -> 0.028045349 | E6: =MAX(Table5[ROE]) -> 0.45685348 | F6: =MAX(Table5[Cash-to-Assets Ratio]) -> 0.11043583 | G6: =MAX(Table5[Financing-to-Assets Ratio]) -> 0.67232001 | H6: =MAX(Table5[[Bank Size ]]) -> 22.456655
A8: ISLAMIC BANKS
A9: Statistic | B9: Operating Expense Ratio | C9: Cost-to-Income Ratio | D9: ROA | E9: ROE | F9: Cash-to-Assets Ratio | G9: Financing-to-Assets Ratio | H9: Bank Size
A10: Mean | B10: =AVERAGE(Ratios!D20:D37) -> 0.024142935 | C10: =AVERAGE(Ratios!E20:E37) -> 0.45346951 | D10: =AVERAGE(Ratios!F20:F37) -> 0.013378463 | E10: =AVERAGE(Ratios!G20:G37) -> 0.21974078 | F10: =AVERAGE(Ratios!H20:H37) -> 0.071051292 | G10: =AVERAGE(Ratios!I20:I37) -> 0.45958155 | H10: =AVERAGE(Ratios!J20:J37) -> 20.383474
A11: Median | B11: =MEDIAN(Ratios!D20:D37) -> 0.023868386 | C11: =MEDIAN(Ratios!E20:E37) -> 0.44300527 | D11: =MEDIAN(Ratios!F20:F37) -> 0.014076247 | E11: =MEDIAN(Ratios!G20:G37) -> 0.17432065 | F11: =MEDIAN(Ratios!H20:H37) -> 0.067128314 | G11: =MEDIAN(Ratios!I20:I37) -> 0.42678933 | H11: =MEDIAN(Ratios!J20:J37) -> 19.967712
A12: Standard Deviation | B12: =_xlfn.STDEV.S(Ratios!D20:D37) -> 0.0042894067 | C12: =_xlfn.STDEV.S(Ratios!E20:E37) -> 0.122211 | D12: =_xlfn.STDEV.S(Ratios!F20:F37) -> 0.0065245453 | E12: =_xlfn.STDEV.S(Ratios!G20:G37) -> 0.1230741 | F12: =_xlfn.STDEV.S(Ratios!H20:H37) -> 0.014550647 | G12: =_xlfn.STDEV.S(Ratios!I20:I37) -> 0.11111742 | H12: =_xlfn.STDEV.S(Ratios!J20:J37) -> 0.87899334
A13: Minimum | B13: =MIN(Ratios!D20:D37) -> 0.017940512 | C13: =MIN(Ratios!E20:E37) -> 0.25167852 | D13: =MIN(Ratios!F20:F37) -> 0.0038408741 | E13: =MIN(Ratios!G20:G37) -> 0.055205101 | F13: =MIN(Ratios!H20:H37) -> 0.045682944 | G13: =MIN(Ratios!I20:I37) -> 0.31926902 | H13: =MIN(Ratios!J20:J37) -> 19.393876
A14: Maximum | B14: =MAX(Ratios!D20:D37) -> 0.034974489 | C14: =MAX(Ratios!E20:E37) -> 0.73168002 | D14: =MAX(Ratios!F20:F37) -> 0.028045349 | E14: =MAX(Ratios!G20:G37) -> 0.45685348 | F14: =MAX(Ratios!H20:H37) -> 0.10245417 | G14: =MAX(Ratios!I20:I37) -> 0.67232001 | H14: =MAX(Ratios!J20:J37) -> 22.084348
A16: CONVENTIONAL BANKS
A17: Statistic | B17: Operating Expense Ratio | C17: Cost-to-Income Ratio | D17: ROA | E17: ROE | F17: Cash-to-Assets Ratio | G17: Financing-to-Assets Ratio | H17: Bank Size
A18: Mean | B18: =AVERAGE(Ratios!D1:D19) -> 0.024170059 | C18: =AVERAGE(Ratios!E1:E19) -> 0.61978894 | D18: =AVERAGE(Ratios!F1:F19) -> 0.0068118932 | E18: =AVERAGE(Ratios!G1:G19) -> 0.12425789 | F18: =AVERAGE(Ratios!H1:H19) -> 0.07114969 | G18: =AVERAGE(Ratios!I1:I19) -> 0.37608618 | H18: =AVERAGE(Ratios!J1:J19) -> 21.135121
A19: Median | B19: =MEDIAN(Ratios!D1:D19) -> 0.022880409 | C19: =MEDIAN(Ratios!E1:E19) -> 0.5714314 | D19: =MEDIAN(Ratios!F1:F19) -> 0.0080578895 | E19: =MEDIAN(Ratios!G1:G19) -> 0.13137302 | F19: =MEDIAN(Ratios!H1:H19) -> 0.070203285 | G19: =MEDIAN(Ratios!I1:I19) -> 0.37365334 | H19: =MEDIAN(Ratios!J1:J19) -> 21.049851
A20: Standard Deviation | B20: =_xlfn.STDEV.S(Ratios!D1:D19) -> 0.0078929339 | C20: =_xlfn.STDEV.S(Ratios!E1:E19) -> 0.15431644 | D20: =_xlfn.STDEV.S(Ratios!F1:F19) -> 0.0034082979 | E20: =_xlfn.STDEV.S(Ratios!G1:G19) -> 0.061968 | F20: =_xlfn.STDEV.S(Ratios!H1:H19) -> 0.019412527 | G20: =_xlfn.STDEV.S(Ratios!I1:I19) -> 0.061881585 | H20: =_xlfn.STDEV.S(Ratios!J1:J19) -> 0.88686377
A21: Minimum | B21: =MIN(Ratios!D1:D19) -> 0.01345073 | C21: =MIN(Ratios!E1:E19) -> 0.39482949 | D21: =MIN(Ratios!F1:F19) -> 5.2405584e-05 | E21: =MIN(Ratios!G1:G19) -> 0.0014222949 | F21: =MIN(Ratios!H1:H19) -> 0.040156226 | G21: =MIN(Ratios!I1:I19) -> 0.27848436 | H21: =MIN(Ratios!J1:J19) -> 19.969151
A22: Maximum | B22: =MAX(Ratios!D1:D19) -> 0.042989977 | C22: =MAX(Ratios!E1:E19) -> 0.98360735 | D22: =MAX(Ratios!F1:F19) -> 0.010930332 | E22: =MAX(Ratios!G1:G19) -> 0.22069642 | F22: =MAX(Ratios!H1:H19) -> 0.11043583 | G22: =MAX(Ratios!I1:I19) -> 0.51643406 | H22: =MAX(Ratios!J1:J19) -> 22.456655

Sheet Trend Chart
A3: 1. Operating Expense Ratio | B3: Banks
A4: Years | B4: Askari | C4: BankIslami | D4: HBL | E4: JS | F4: Meezan | G4: Dubai Islamic Bank
A5: 2019 | B5: 0.021885756 | C5: 0.027273969 | D5: 0.027084615 | E5: 0.022940241 | F5: 0.022145352 | G5: 0.025161509
A6: 2020 | B6: 0.020275213 | C6: 0.025507318 | D6: 0.022820578 | E6: 0.024464061 | F6: 0.018933575 | G6: 0.024301324
A7: 2021 | B7: 0.016591052 | C7: 0.023383555 | D7: 0.020764727 | E7: 0.021774679 | F7: 0.018054025 | G7: 0.02357375
A8: 2022 | B8: 0.01479057 | C8: 0.024163021 | D8: 0.025366889 | E8: 0.027158338 | F8: 0.017940512 | G8: 0.022748689
A9: 2023 | B9: 0.01345073 | C9: 0.024676283 | D9: 0.029286614 | E9: 0.039091086 | F9: 0.022534576 | G9: 0.028783353
A10: 2024 | B10: 0.014172614 | C10: 0.030032597 | D10: 0.030153324 | E10: 0.042989977 | F10: 0.020384927 | G10: 0.034974489
A12: 2. Cost-to-Income Ratio | B12: Banks
A13: Years | B13: Askari | C13: BankIslami | D13: HBL | E13: JS | F13: Meezan | G13: Dubai Islamic Bank
A14: 2019 | B14: 0.61731174 | C14: 0.62149301 | D14: 0.72945524 | E14: 0.98360735 | F14: 0.44451936 | G14: 0.50127523
A15: 2020 | B15: 0.50363359 | C15: 0.60732352 | D15: 0.56261537 | E15: 0.7912531 | F15: 0.38452029 | G15: 0.512118
A16: 2021 | B16: 0.50002009 | C16: 0.73168002 | D16: 0.55783453 | E16: 0.74965436 | F16: 0.40991648 | G16: 0.53271571
A17: 2022 | B17: 0.43760578 | C17: 0.49052375 | D17: 0.58024744 | E17: 0.83096546 | F17: 0.328392 | G17: 0.44149118
A18: 2023 | B18: 0.39482949 | C18: 0.37153478 | D18: 0.54937204 | E18: 0.66567905 | F18: 0.27310571 | G18: 0.36239832
A19: 2024 | B19: 0.44979999 | C19: 0.43468626 | D19: 0.54483538 | E19: 0.70748084 | F19: 0.25167852 | G19: 0.46307912
A21: 3. ROA | B21: Banks
A22: Years | B22: Askari | C22: BankIslami | D22: HBL | E22: JS | F22: Meezan | G22: Dubai Islamic Bank
A23: 2019 | B23: 0.008421693 | C23: 0.0038408741 | D23: 0.0049330394 | E23: 5.2405584e-05 | F23: 0.013584804 | G23: 0.012642134
A24: 2020 | B24: 0.010881803 | C24: 0.0050643731 | D24: 0.0086515302 | E24: 0.0021610828 | F24: 0.01456769 | G24: 0.0095425389
A25: 2021 | B25: 0.0077047464 | C25: 0.0052189062 | D25: 0.0084110325 | E25: 0.0022324437 | F25: 0.014900464 | G25: 0.0087895793
A26: 2022 | B26: 0.0092138681 | C26: 0.0091118198 | D26: 0.0070875582 | E26: 0.001564381 | F26: 0.017462037 | G26: 0.0087913288
A27: 2023 | B27: 0.010091619 | C27: 0.0168662 | D27: 0.010930332 | E27: 0.0073543931 | F27: 0.028045349 | G27: 0.015590018
A28: 2024 | B28: 0.0084145405 | C28: 0.016038215 | D28: 0.010029644 | E28: 0.0044779649 | F28: 0.026024825 | G28: 0.01473117

Sheet Comparison Charts
A1: Operating Expenses Ratio | E1: Cost to Income Ratio
A2: Year | B2: Islamic Average | C2: Conventional Average | E2: Year | F2: Islamic Average | G2: Conventional Average
A3: 2019 | B3: =AVERAGEIFS(Ratios!$D$2:$D$37,Ratios!$B$2:$B$37,"Islamic",Ratios!$C$2:$C$37,A3) -> 0.024860277 | C3: =AVERAGEIFS(Ratios!$D$2:$D$37,Ratios!$B$2:$B$37,"Conventional",Ratios!$C$2:$C$37,A3) -> 0.023970204 | E3: 2019 | F3: =AVERAGEIFS(Ratios!$E$2:$E$37,Ratios!$B$2:$B$37,"Islamic",Ratios!$C$2:$C$37,E3) -> 0.5224292 | G3: =AVERAGEIFS(Ratios!$E$2:$E$37,Ratios!$B$2:$B$37,"Conventional",Ratios!$C$2:$C$37,E3) -> 0.77679144
A4: 2020 | B4: =AVERAGEIFS(Ratios!$D$2:$D$37,Ratios!$B$2:$B$37,"Islamic",Ratios!$C$2:$C$37,A4) -> 0.022914072 | C4: =AVERAGEIFS(Ratios!$D$2:$D$37,Ratios!$B$2:$B$37,"Conventional",Ratios!$C$2:$C$37,A4) -> 0.022519951 | E4: 2020 | F4: =AVERAGEIFS(Ratios!$E$2:$E$37,Ratios!$B$2:$B$37,"Islamic",Ratios!$C$2:$C$37,E4) -> 0.5013206 | G4: =AVERAGEIFS(Ratios!$E$2:$E$37,Ratios!$B$2:$B$37,"Conventional",Ratios!$C$2:$C$37,E4) -> 0.61916735
A5: 2021 | B5: =AVERAGEIFS(Ratios!$D$2:$D$37,Ratios!$B$2:$B$37,"Islamic",Ratios!$C$2:$C$37,A5) -> 0.021670443 | C5: =AVERAGEIFS(Ratios!$D$2:$D$37,Ratios!$B$2:$B$37,"Conventional",Ratios!$C$2:$C$37,A5) -> 0.019710153 | E5: 2021 | F5: =AVERAGEIFS(Ratios!$E$2:$E$37,Ratios!$B$2:$B$37,"Islamic",Ratios!$C$2:$C$37,E5) -> 0.55810407 | G5: =AVERAGEIFS(Ratios!$E$2:$E$37,Ratios!$B$2:$B$37,"Conventional",Ratios!$C$2:$C$37,E5) -> 0.60250299
A6: 2022 | B6: =AVERAGEIFS(Ratios!$D$2:$D$37,Ratios!$B$2:$B$37,"Islamic",Ratios!$C$2:$C$37,A6) -> 0.021617407 | C6: =AVERAGEIFS(Ratios!$D$2:$D$37,Ratios!$B$2:$B$37,"Conventional",Ratios!$C$2:$C$37,A6) -> 0.022438599 | E6: 2022 | F6: =AVERAGEIFS(Ratios!$E$2:$E$37,Ratios!$B$2:$B$37,"Islamic",Ratios!$C$2:$C$37,E6) -> 0.42013564 | G6: =AVERAGEIFS(Ratios!$E$2:$E$37,Ratios!$B$2:$B$37,"Conventional",Ratios!$C$2:$C$37,E6) -> 0.61627289
A7: 2023 | B7: =AVERAGEIFS(Ratios!$D$2:$D$37,Ratios!$B$2:$B$37,"Islamic",Ratios!$C$2:$C$37,A7) -> 0.025331404 | C7: =AVERAGEIFS(Ratios!$D$2:$D$37,Ratios!$B$2:$B$37,"Conventional",Ratios!$C$2:$C$37,A7) -> 0.027276143 | E7: 2023 | F7: =AVERAGEIFS(Ratios!$E$2:$E$37,Ratios!$B$2:$B$37,"Islamic",Ratios!$C$2:$C$37,E7) -> 0.3356796 | G7: =AVERAGEIFS(Ratios!$E$2:$E$37,Ratios!$B$2:$B$37,"Conventional",Ratios!$C$2:$C$37,E7) -> 0.53662686
A8: 2024 | B8: =AVERAGEIFS(Ratios!$D$2:$D$37,Ratios!$B$2:$B$37,"Islamic",Ratios!$C$2:$C$37,A8) -> 0.028464004 | C8: =AVERAGEIFS(Ratios!$D$2:$D$37,Ratios!$B$2:$B$37,"Conventional",Ratios!$C$2:$C$37,A8) -> 0.029105305 | E8: 2024 | F8: =AVERAGEIFS(Ratios!$E$2:$E$37,Ratios!$B$2:$B$37,"Islamic",Ratios!$C$2:$C$37,E8) -> 0.38314797 | G8: =AVERAGEIFS(Ratios!$E$2:$E$37,Ratios!$B$2:$B$37,"Conventional",Ratios!$C$2:$C$37,E8) -> 0.56737207
A14: Cash-to-Assets Ratio
A15: Year | B15: Islamic Average | C15: Conventional Average
A16: 2019 | B16: =AVERAGEIFS(Ratios!$H$2:$H$37,Ratios!$B$2:$B$37,"Islamic",Ratios!$C$2:$C$37,A16) -> 0.069103631 | C16: =AVERAGEIFS(Ratios!$H$2:$H$37,Ratios!$B$2:$B$37,"Conventional",Ratios!$C$2:$C$37,A16) -> 0.080163455
A17: 2020 | B17: =AVERAGEIFS(Ratios!$H$2:$H$37,Ratios!$B$2:$B$37,"Islamic",Ratios!$C$2:$C$37,A17) -> 0.072677465 | C17: =AVERAGEIFS(Ratios!$H$2:$H$37,Ratios!$B$2:$B$37,"Conventional",Ratios!$C$2:$C$37,A17) -> 0.075625198
A18: 2021 | B18: =AVERAGEIFS(Ratios!$H$2:$H$37,Ratios!$B$2:$B$37,"Islamic",Ratios!$C$2:$C$37,A18) -> 0.074337249 | C18: =AVERAGEIFS(Ratios!$H$2:$H$37,Ratios!$B$2:$B$37,"Conventional",Ratios!$C$2:$C$37,A18) -> 0.076727125
A19: 2022 | B19: =AVERAGEIFS(Ratios!$H$2:$H$37,Ratios!$B$2:$B$37,"Islamic",Ratios!$C$2:$C$37,A19) -> 0.076725433 | C19: =AVERAGEIFS(Ratios!$H$2:$H$37,Ratios!$B$2:$B$37,"Conventional",Ratios!$C$2:$C$37,A19) -> 0.048580711
A20: 2023 | B20: =AVERAGEIFS(Ratios!$H$2:$H$37,Ratios!$B$2:$B$37,"Islamic",Ratios!$C$2:$C$37,A20) -> 0.070216959 | C20: =AVERAGEIFS(Ratios!$H$2:$H$37,Ratios!$B$2:$B$37,"Conventional",Ratios!$C$2:$C$37,A20) -> 0.080623292
A21: 2024 | B21: =AVERAGEIFS(Ratios!$H$2:$H$37,Ratios!$B$2:$B$37,"Islamic",Ratios!$C$2:$C$37,A21) -> 0.063247016 | C21: =AVERAGEIFS(Ratios!$H$2:$H$37,Ratios!$B$2:$B$37,"Conventional",Ratios!$C$2:$C$37,A21) -> 0.065178361

Sheet Distribution Charts

Sheet Comparitive Analysis
A3: Bank Type | B3: Average of Operating Expense Ratio | C3: Average of Cost-to-Income Ratio | D3: Average of ROA | E3: Average of ROE | F3: Average of Cash-to-Assets Ratio | G3: Average of Financing-to-Assets Ratio
A4: Conventional | B4: 0.024170059 | C4: 0.61978894 | D4: 0.0068118932 | E4: 0.12425789 | F4: 0.07114969 | G4: 0.37608618
A5: Islamic | B5: 0.024142935 | C5: 0.45346951 | D5: 0.013378463 | E5: 0.21974078 | F5: 0.071051292 | G5: 0.45958155
A6: % Diff | B6: =(GETPIVOTDATA("Average of Operating Expense Ratio",$A$3,"Bank Type","Islamic")-GETPIVOTDATA("Average of Operating Expense Ratio",$A$3,"Bank Type","Conventional"))/GETPIVOTDATA("Average of Operating Expense Ratio",$A$3,"Bank Type","Conventional") -> -0.0011222311 | C6: =(GETPIVOTDATA("Average of Cost-to-Income Ratio",$A$3,"Bank Type","Islamic")-GETPIVOTDATA("Average of Cost-to-Income Ratio",$A$3,"Bank Type","Conventional"))/GETPIVOTDATA("Average of Cost-to-Income Ratio",$A$3,"Bank Type","Conventional") -> -0.26834848 | D6: =(GETPIVOTDATA("Average of ROA",$A$3,"Bank Type","Islamic")-GETPIVOTDATA("Average of ROA",$A$3,"Bank Type","Conventional"))/GETPIVOTDATA("Average of ROA",$A$3,"Bank Type","Conventional") -> 0.96398595 | E6: =(GETPIVOTDATA("Average of ROE",$A$3,"Bank Type","Islamic")-GETPIVOTDATA("Average of ROE",$A$3,"Bank Type","Conventional"))/GETPIVOTDATA("Average of ROE",$A$3,"Bank Type","Conventional") -> 0.7684251 | F6: =(GETPIVOTDATA("Average of Cash-to-Assets Ratio",$A$3,"Bank Type","Islamic")-GETPIVOTDATA("Average of Cash-to-Assets Ratio",$A$3,"Bank Type","Conventional"))/GETPIVOTDATA("Average of Cash-to-Assets Ratio",$A$3,"Bank Type","Conventional") -> -0.0013829735 | G6: =(GETPIVOTDATA("Average of Financing-to-Assets Ratio",$A$3,"Bank Type","Islamic")-GETPIVOTDATA("Average of Financing-to-Assets Ratio",$A$3,"Bank Type","Conventional"))/GETPIVOTDATA("Average of Financing-to-Assets Ratio",$A$3,"Bank Type","Conventional") -> 0.22201124

Sheet Staff Comparison
A1: Bank_Type | B1: (All)
A3: Staff Strength Comparison | B3: Years
A4: Banks | B4: 2019 | C4: 2020 | D4: 2021 | E4: 2022 | F4: 2023 | G4: 2024
A5: Askari | B5: 7848 | C5: 7949 | D5: 7478 | E5: 7348 | F5: 7881 | G5: 8269
A6: BankIslami | B6: 3447 | C6: 3437 | D6: 4046 | E6: 4562 | F6: 5891 | G6: 7317
A7: Dubai Islamic Bank | B7: 3095 | C7: 3099 | D7: 3223 | E7: 3468 | F7: 3434 | G7: 3774
A8: HBL | B8: 17353 | C8: 16954 | D8: 17591 | E8: 17602 | F8: 16353 | G8: 16533
A9: JS | B9: 4904 | C9: 5311 | D9: 4487 | E9: 4739 | F9: 4940 | G9: 5142
A10: Meezan | B10: 11649 | C10: 12423 | D10: 14007 | E10: 15380 | F10: 17186 | G10: 18653

Sheet Variable Dictionary
A1: Variable/Ratio | B1: Formula Applied | C1: Where to Find
A2: Operating Expense Ratio | B2: Operating Expenses ÷ Total Assets | C2: Income Statement ÷ Balance Sheet
A3: Cost-to-Income Ratio | B3: Operating Expenses ÷ Operating Income | C3: Income Statement
A4: ROA | B4: Net Profit ÷ Total Assets | C4: Income Statement ÷ Balance Sheet
A5: ROE | B5: Net Profit ÷ Total Equity | C5: Income Statement ÷ Balance Sheet
A6: Cash-to-Assets Ratio | B6: Cash ÷ Total Assets | C6: Balance Sheet
A7: Financing/Loans-to-Assets | B7: Financing (or Loans) ÷ Total Assets | C7: Balance Sheet
A8: Deposit Return | B8: Profit Distributed to Depositors ÷ Total Deposits | C8: Notes to Accounts
A9: Bank Size | B9: Natural log of Total Assets — =LN(TotalAssets) in Excel | C9: Balance Sheet

Sheet Literature
A1: Paper (Author, Year) | B1: Objective | C1: Method | D1: Variables Used | E1: Key Finding | F1: Gap
A2: Akhtar, Ali & Sadaqat (2011) — Factors Influencing the Profitability of Islamic Banks of Pakistan | B2: Test how bank-specific factors affect Islamic bank profitability in Pakistan, 2006-2009 | C2: OLS regression, two models (ROA, ROE) | D2: DVs: ROA, ROE. IVs: Size, Gearing Ratio, NPLs Ratio, Asset Management, Capital Adequacy, Operating Efficiency | E2: Operating efficiency (cost ratio) has a significant NEGATIVE relationship with both ROA and ROE. Gearing ratio and capital adequacy positively significant | F2: Studies Islamic banks only — no conventional comparator, so never tests if the cost burden is structurally higher than a peer's
A3: Bader, Mohamad, Ariff & Hassan — Cost, Revenue, and Profit Efficiency of Conventional versus Islamic Banks | B3: Compare cost/revenue/profit efficiency of Islamic vs conventional banks, 21 OIC countries | C3: Financial ratios + t-tests/ANOVA by size, age, region | D3: CTIR, NIER (cost); NIM, OPIR (revenue); ROAA, ROAE (profit | E3: No statistically significant difference in cost, revenue, or profit efficiency between the two banking streams, overall or by subgroup | F3: Cross-country pooled sample, not Pakistan-specific — masks country-level regulatory effects; no depositor-return link
A4: Khan & Shah (2015) — Cost Efficiency and Total Factor Productivity of Islamic and Conventional Banks in Pakistan | B4: Compare cost efficiency and TFP growth of Islamic, conventional, and Islamic-window banks in Pakistan, 2007-2011 | C4: DEA (CRS) for cost efficiency; Malmquist Index for TFP; Tobit regression | D4: DEA inputs: employees, fixed assets, deposits. Outputs: loans, other income, investments. Tobit IVs: ROE, Debt, Size, Deposits | E4: Islamic banks' cost efficiency (0.554) is ~35% lower than conventional (0.910) — significant. Islamic banks show highest TFP growth (1.164) | F4: Small sample (5 banks/category), dated window (2007-2011), uses a DEA score not a direct cost ratio, no depositor-return link
A5: Qureshi & Shaikh (2012) — Efficiency of Islamic and Conventional Banks in Pakistan: A Non-parametric Approach | B5: Compare efficiency of one Islamic, one conventional, one Islamic-window bank, 2003-2008 | C5: Ratio analysis (CTI, NIE, NIM, OOI, ROA, ROE) + DEA (CCR/BCC, window analysis) | D5: Cost-to-Income, Non-Interest Expense/Assets, NIM, Other Op. Income/Assets, ROA, ROE, DEA scores | E5: Conventional bank most cost efficient throughout; Islamic bank generally cost inefficient — attributed explicitly to Shariah board costs and legal complexity of Islamic contract | F5: Single-bank case study per category (n=1) — can't generalize statistically; names Shariah-governance overhead as driver, untested across multiple banks
A6: Akhtar, Ali & Sadaqat (2011) — Liquidity Risk Management: A comparative study between Conventional and Islamic Banks of Pakistan | B6: Compare liquidity risk determinants, 6 conventional vs 6 Islamic banks, 2006-2009 | C6: Pooled OLS, two models | D6: DV: Liquidity Risk (Cash/Total Assets). IVs: Size, Net Working Capital, ROE, CAR, ROA | E6: Conventional banks: CAR positive & significant. Islamic banks: ROA positive & significant, ROE negative & significant. Conventional banks show stronger overall liquidity management | F6: Liquidity focus only, not cost structure; sample ends 2009, 15 years before your window; no depositor-return link
A7: Hassan — The Cost, Profit and X-Efficiency of Islamic Banks (ERF Conference Paper) | B7: Examine cost, profit, revenue, X-efficiency of 43 Islamic banks, 21 countries, 1995-2001, no conventional comparator | C7: Stochastic Frontier Analysis, DEA (CRS/VRS), Malmquist TFP, second-stage regression | D7: Cost function inputs: labor, capital, funds. DEA outputs: loans, earning assets, off-balance-sheet items | E7: Average cost efficiency ~74% vs profit efficiency ~84% — Islamic banks worse at controlling costs than generating profit. Allocative (regulatory) inefficiency dominates technical inefficiency | F7: No conventional comparator at all; global sample, not Pakistan-specific, misses SBP's dual-regulatory environment
A8: Majeed & Zanib (2016) — Efficiency analysis of Islamic banks in Pakistan (Humanomics) | B8: Compare efficiency of full-fledged Islamic banks, Islamic branches of conventional banks, and conventional banks, 2007-2014 | C8: DEA — total technical, pure technical, and scale efficiency (abstract only, paywalled) | D8: DEA-based efficiency scores (inputs/outputs not visible from abstract) | E8: Full-fledged Islamic banks less efficient than conventional banks on total and pure technical efficiency. Islamic branches (windows) of conventional banks are highly scale-efficient | F8: Only abstract accessible; full-fledged vs window-branch distinction untested in your sample, since all 3 Islamic banks chosen are full-fledged
A9: Khan, Khan & Tahir (2017) — Performance comparison of Islamic and conventional banks: empirical evidence from Pakistan | B9: Compare profitability, efficiency, risk, liquidity, asset quality — 5 Islamic vs 19 conventional banks, 2007-2014, with crisis sub-sample | C9: Independent-samples t-test, logistic regression (abstract only, paywalled) | D9: Financial ratios across profitability, efficiency, risk, liquidity, asset quality (specific list not visible from abstract) | E9: Islamic banks relatively BETTER in profitability, efficiency, risk, liquidity management; conventional banks superior in asset quality. During crisis, Islamic banks were less profitable | F9: Directly contradicts Khan & Shah (2015) and Qureshi & Shaikh (2012) above — this is an unsettled question in the Pakistan literature, the strongest justification for re-testing on 2019-2024 data

Sheet Notes
A1: Bank & Year | B1: Item | C1: Page | D1: Mentioned As | E1: Statement
A2: Askari Bank 2019 | B2: Total Assets | C2: 47 | D2: (unlabeled subtotal after "Other assets") | E2: Unconsolidated Statement of Financial Position
A3: Askari Bank 2019 | B3: Total Deposits | C3: 47 | D3: Deposits and other accounts | E3: Unconsolidated Statement of Financial Position
A4: Askari Bank 2019 | B4: Total Equity | C4: 47 | D4: Net Assets (Represented by total) | E4: Unconsolidated Statement of Financial Position
A5: Askari Bank 2019 | B5: Cash | C5: 47 | D5: Cash and balances with treasury banks | E5: Unconsolidated Statement of Financial Position
A6: Askari Bank 2019 | B6: Financing/Loans | C6: 47 | D6: Advances | E6: Unconsolidated Statement of Financial Position
A7: Askari Bank 2019 | B7: Operating Income | C7: 48 | D7: Total income | E7: Unconsolidated Profit and Loss Account
A8: Askari Bank 2019 | B8: Operating Expenses | C8: 48 | D8: Operating expenses | E8: Unconsolidated Profit and Loss Account
A9: Askari Bank 2019 | B9: Staff Expenses | C9: 87 | D9: Total compensation expenses (Note 29.1) | E9: Notes to Unconsolidated Financial Statements
A10: Askari Bank 2019 | B10: Net Profit | C10: 48 | D10: Profit after taxation | E10: Unconsolidated Profit and Loss Account
A11: Askari Bank 2019 | B11: Profit Distributed | C11: 22 | D11: Cash dividend - 15 percent | E11: Appropriations table Directors Report
A12: Askari Bank 2020 | B12: Total Assets | C12: 53 | D12: (unlabeled subtotal after "Other assets") | E12: Unconsolidated Statement of Financial Position
A13: Askari Bank 2020 | B13: Total Deposits | C13: 53 | D13: Deposits and other accounts | E13: Unconsolidated Statement of Financial Position
... A121: HBL 2024 | B121: Profit Distributed | C121: 27 | D121: Cash dividend Final + 1st/2nd/3rd interim | E121: Movement in Reserves (Appropriations), Directors' Report
